craft_application/__init__.py
craft_application/_config.py
craft_application/_const.py
craft_application/_version.py
craft_application/application.py
craft_application/errors.py
craft_application/fetch.py
craft_application/grammar.py
craft_application/py.typed
craft_application/pytest_plugin.py
craft_application/commands/__init__.py
craft_application/commands/base.py
craft_application/commands/init.py
craft_application/commands/lifecycle.py
craft_application/commands/other.py
craft_application/commands/remote.py
craft_application/git/__init__.py
craft_application/git/_consts.py
craft_application/git/_errors.py
craft_application/git/_git_repo.py
craft_application/git/_models.py
craft_application/git/_utils.py
craft_application/launchpad/__init__.py
craft_application/launchpad/errors.py
craft_application/launchpad/launchpad.py
craft_application/launchpad/util.py
craft_application/launchpad/models/__init__.py
craft_application/launchpad/models/base.py
craft_application/launchpad/models/build.py
craft_application/launchpad/models/code.py
craft_application/launchpad/models/distro.py
craft_application/launchpad/models/project.py
craft_application/launchpad/models/recipe.py
craft_application/misc/instance_bashrc
craft_application/models/__init__.py
craft_application/models/base.py
craft_application/models/constraints.py
craft_application/models/grammar.py
craft_application/models/manifest.py
craft_application/models/metadata.py
craft_application/models/platforms.py
craft_application/models/project.py
craft_application/models/spread.py
craft_application/models/state.py
craft_application/remote/__init__.py
craft_application/remote/errors.py
craft_application/remote/git.py
craft_application/remote/utils.py
craft_application/remote/worktree.py
craft_application/services/__init__.py
craft_application/services/base.py
craft_application/services/buildplan.py
craft_application/services/config.py
craft_application/services/fetch.py
craft_application/services/init.py
craft_application-6.1.0.dist-info/licenses/LICENSE
craft_application-6.1.0.dist-info/METADATA
craft_application-6.1.0.dist-info/WHEEL
craft_application-6.1.0.dist-info/entry_points.txt
craft_application-6.1.0.dist-info/top_level.txt
craft_application-6.1.0.dist-info/RECORD
