Metadata-Version: 2.4
Name: craft-application
Version: 6.1.0
Summary: A framework for *craft applications.
License:                    GNU LESSER GENERAL PUBLIC LICENSE
Classifier: Development Status :: 5 - Production/Stable
Classifier: Environment :: Console
Classifier: Intended Audience :: Developers
Classifier: Operating System :: POSIX :: Linux
Classifier: Programming Language :: Python :: 3.10
Classifier: Programming Language :: Python :: 3.12
Classifier: Topic :: Software Development :: Libraries :: Application Frameworks
Classifier: Topic :: Software Development :: Libraries :: Python Modules
Classifier: Typing :: Typed
Requires-Python: >=3.10
License-File: LICENSE
Requires-Dist: annotated-types>=0.6.0
Requires-Dist: craft-archives>=2.2.0
Requires-Dist: craft-cli>=3.2.0
Requires-Dist: craft-grammar>=2.3.0
Requires-Dist: craft-parts>=2.28.0
Requires-Dist: craft-platforms>=0.6.0
Requires-Dist: craft-providers>=3.2.0
Requires-Dist: Jinja2<4.0.0,>=3.1.6
Requires-Dist: snap-helpers>=0.4.2
Requires-Dist: platformdirs>=3.10
Requires-Dist: pydantic~=2.0
Requires-Dist: license-expression>=30.0.0
Requires-Dist: pygit2<1.19.0,>=1.13.0
Requires-Dist: PyYaml>=6.0
Requires-Dist: requests
Requires-Dist: typing_extensions>=4.4.0
Requires-Dist: distro-support>=2025.12.16
Provides-Extra: remote
Requires-Dist: launchpadlib>=1.10.16; extra == "remote"
Requires-Dist: pysocks>=1.7.1; extra == "remote"
Provides-Extra: apt
Requires-Dist: python-apt>=2.4.0; sys_platform == "linux" and extra == "apt"
Dynamic: license-file
